{
  "id": "central",
  "name": "Central Livestock Association",
  "location": "Zumbrota MN",
  "lastUpdated": "2026-03-22",
  "lastSuccess": "2026-03-09",
  "history": [
    {
      "date": "2026-03-21",
      "slaughter": {
        "beef": null,
        "crossbred": null,
        "holstein": null
      },
      "feeder": {
        "beef": null,
        "crossbred": null,
        "holstein": null,
        "liteTest": false
      },
      "source": "fetch_failed",
      "error": "zero prices extracted — page structure may have changed"
    },
    {
      "date": "2026-03-22",
      "slaughter": {
        "beef": 231.5,
        "crossbred": 227.5,
        "holstein": 205.5
      },
      "feeder": {
        "beef": 405,
        "crossbred": 401.2,
        "holstein": 203,
        "liteTest": true
      },
      "feederWeights": [
        {
          "range": "350–600#",
          "price": 405,
          "types": [
            "beef",
            "crossbred"
          ]
        },
        {
          "range": "600–800#",
          "price": 335,
          "types": [
            "beef",
            "crossbred"
          ]
        },
        {
          "range": "800–1000#",
          "price": 255,
          "types": [
            "beef",
            "crossbred"
          ]
        },
        {
          "range": "600–800#",
          "price": 350,
          "types": [
            "beef",
            "crossbred"
          ]
        },
        {
          "range": "800–1000#",
          "price": 240,
          "types": [
            "beef",
            "crossbred"
          ]
        },
        {
          "range": "400–600#",
          "price": 300,
          "types": [
            "holstein"
          ]
        }
      ],
      "saleDay": null,
      "liteTestNote": null,
      "repSales": {
        "finishWeightAvgs": [
          {
            "range": "1100-1199 lbs",
            "type": "beef",
            "avgPrice": 239,
            "head": 1
          },
          {
            "range": "1200-1299 lbs",
            "type": "crossbred",
            "avgPrice": 257.5,
            "head": 5
          },
          {
            "range": "1300-1399 lbs",
            "type": "beef",
            "avgPrice": 227,
            "head": 5
          },
          {
            "range": "1400-1499 lbs",
            "type": "crossbred",
            "avgPrice": 232,
            "head": 20
          },
          {
            "range": "1400-1499 lbs",
            "type": "beef",
            "avgPrice": 235,
            "head": 5
          },
          {
            "range": "1500-1599 lbs",
            "type": "beef",
            "avgPrice": 239.83,
            "head": 3
          },
          {
            "range": "1500-1599 lbs",
            "type": "crossbred",
            "avgPrice": 224.5,
            "head": 5
          },
          {
            "range": "1600-1699 lbs",
            "type": "beef",
            "avgPrice": 233.5,
            "head": 3
          },
          {
            "range": "1600-1699 lbs",
            "type": "crossbred",
            "avgPrice": 231,
            "head": 8
          },
          {
            "range": "1600-1699 lbs",
            "type": "holstein",
            "avgPrice": 207,
            "head": 3
          },
          {
            "range": "1700-1799 lbs",
            "type": "beef",
            "avgPrice": 229.5,
            "head": 1
          },
          {
            "range": "1700-1799 lbs",
            "type": "holstein",
            "avgPrice": 207,
            "head": 4
          },
          {
            "range": "1800-1899 lbs",
            "type": "beef",
            "avgPrice": 230.75,
            "head": 2
          },
          {
            "range": "1800-1899 lbs",
            "type": "holstein",
            "avgPrice": 204,
            "head": 1
          }
        ],
        "feederWeightAvgs": [
          {
            "range": "400-499 lbs",
            "type": "beef",
            "avgPrice": 345,
            "head": 1
          },
          {
            "range": "600-699 lbs",
            "type": "beef",
            "avgPrice": 350,
            "head": 2
          }
        ],
        "headCount": {
          "finished": 66,
          "feeder": 3,
          "bulls": 7,
          "cows": 31
        }
      },
      "source": "scraped"
    }
  ]
}
